DracoPy.cpython-313-darwin.so
dracopy-2.0.0.data/data/bin/draco_decoder
dracopy-2.0.0.data/data/bin/draco_decoder-1.5.7
dracopy-2.0.0.data/data/bin/draco_encoder
dracopy-2.0.0.data/data/bin/draco_encoder-1.5.7
dracopy-2.0.0.data/data/include/draco/draco_features.h
dracopy-2.0.0.data/data/include/draco/animation/keyframe_animation.h
dracopy-2.0.0.data/data/include/draco/animation/keyframe_animation_decoder.h
dracopy-2.0.0.data/data/include/draco/animation/keyframe_animation_encoder.h
dracopy-2.0.0.data/data/include/draco/attributes/attribute_octahedron_transform.h
dracopy-2.0.0.data/data/include/draco/attributes/attribute_quantization_transform.h
dracopy-2.0.0.data/data/include/draco/attributes/attribute_transform.h
dracopy-2.0.0.data/data/include/draco/attributes/attribute_transform_data.h
dracopy-2.0.0.data/data/include/draco/attributes/attribute_transform_type.h
dracopy-2.0.0.data/data/include/draco/attributes/geometry_attribute.h
dracopy-2.0.0.data/data/include/draco/attributes/geometry_indices.h
dracopy-2.0.0.data/data/include/draco/attributes/point_attribute.h
dracopy-2.0.0.data/data/include/draco/compression/decode.h
dracopy-2.0.0.data/data/include/draco/compression/draco_compression_options.h
dracopy-2.0.0.data/data/include/draco/compression/encode.h
dracopy-2.0.0.data/data/include/draco/compression/encode_base.h
dracopy-2.0.0.data/data/include/draco/compression/expert_encode.h
dracopy-2.0.0.data/data/include/draco/compression/attributes/attributes_decoder.h
dracopy-2.0.0.data/data/include/draco/compression/attributes/attributes_decoder_interface.h
dracopy-2.0.0.data/data/include/draco/compression/attributes/attributes_encoder.h
dracopy-2.0.0.data/data/include/draco/compression/attributes/kd_tree_attributes_decoder.h
dracopy-2.0.0.data/data/include/draco/compression/attributes/kd_tree_attributes_encoder.h
dracopy-2.0.0.data/data/include/draco/compression/attributes/kd_tree_attributes_shared.h
dracopy-2.0.0.dist-info/licenses/LICENSE
dracopy-2.0.0.dist-info/METADATA
dracopy-2.0.0.dist-info/WHEEL
dracopy-2.0.0.dist-info/top_level.txt
dracopy-2.0.0.dist-info/RECORD
