Metadata-Version: 2.1
Name: DracoPy
Version: 2.0.0
Summary: Python wrapper for Google's Draco Mesh Compression Library
Home-page: https://github.com/seung-lab/DracoPy
Author: Manuel Castro, William Silversmith :: Contributors :: Fatih Erol, Faru Nuri Sonmez,  Forrest Collman, Zeyu Zhao, Denis Riviere, Brett Tully, Hanseul Jun,  Afshawn Lotfi, Pan Xinmiao, Kenneth Bongort, Ed Schmerling
Author-email: macastro@princeton.edu, ws9@princeton.edu
License: Apache-2.0
Classifier: Intended Audience :: Developers
Classifier: Development Status :: 5 - Production/Stable
Classifier: Programming Language :: Python
Classifier: Programming Language :: Python :: 3
Classifier: Programming Language :: Python :: 3.8
Classifier: Programming Language :: Python :: 3.9
Classifier: Programming Language :: Python :: 3.10
Classifier: Programming Language :: Python :: 3.11
Classifier: Programming Language :: Python :: 3.12
Classifier: Programming Language :: Python :: 3.13
Classifier: Programming Language :: Python :: 3.14
Classifier: Topic :: Scientific/Engineering
Classifier: Operating System :: POSIX
Classifier: Operating System :: MacOS
Classifier: Operating System :: Microsoft :: Windows :: Windows 10
Classifier: Topic :: Utilities
License-File: LICENSE
